Workbook

Sheet Raw Releases
A1: Raw Releases — every USD High/Medium release with numeric actual+forecast in the events archive (the exact universe fx_strict_battery.py computes z on). One block per release title, oldest to newest.
A2: Stats for a title are computed ONLY from rows above it within its own block (expanding, prior events only).
A4: ADP Employment Change (137 events)
A5: Date | B5: Impact | C5: Forecast | D5: Actual
A6: 42011 | B6: Medium | C6: 226 | D6: 241
A7: 42039 | B7: Medium | C7: 225 | D7: 213
A8: 42067 | B8: Medium | C8: 220 | D8: 212
A9: 42095 | B9: Medium | C9: 225 | D9: 189
A10: 42130 | B10: Medium | C10: 200 | D10: 169
A11: 42158 | B11: Medium | C11: 200 | D11: 201
A12: 42186 | B12: Medium | C12: 218 | D12: 237
A13: 42221 | B13: Medium | C13: 215 | D13: 185
A14: 42249 | B14: Medium | C14: 201 | D14: 190
A15: 42277 | B15: Medium | C15: 194 | D15: 200
A16: 42312 | B16: Medium | C16: 180 | D16: 182
A17: 42340 | B17: Medium | C17: 190 | D17: 217
... A142: 46239 | B142: Medium | C142: 70 | D142: 44
A143: API Crude Oil Stock Change (288 events)
A144: Date | B144: Impact | C144: Forecast | D144: Actual
A145: 43096 | B145: Medium | C145: -3.8 | D145: -6
A146: 43109 | B146: Medium | C146: -3.9 | D146: -11.19
A147: 43123 | B147: Medium | C147: -1.6 | D147: 4.755
A148: 43158 | B148: Medium | C148: 2.7 | D148: 0.933
A149: 43186 | B149: Medium | C149: 1 | D149: 5.321
A150: 43207 | B150: Medium | C150: -2.1 | D150: -1.047
A151: 43235 | B151: Medium | C151: -2 | D151: 4.854
A152: 43242 | B152: Medium | C152: -3 | D152: -1.3
A153: 43263 | B153: Medium | C153: -2.8 | D153: -0.73
A154: 43375 | B154: Medium | C154: 1.5 | D154: 0.907
A155: 43452 | B155: Medium | C155: -2.45 | D155: 3.45
A156: 43473 | B156: Medium | C156: -3.4 | D156: -6.27
... A432: 46238 | B432: Medium | C432: -2 | D432: 2.69
A433: Average Hourly Earnings MoM (56 events)
A434: Date | B434: Impact | C434: Forecast | D434: Actual
A435: 44533 | B435: Medium | C435: 0.4 | D435: 0.3
A436: 44568 | B436: Medium | C436: 0.4 | D436: 0.6
A437: 44596 | B437: Medium | C437: 0.5 | D437: 0.7
A438: 44624 | B438: Medium | C438: 0.5 | D438: 0
A439: 44652 | B439: Medium | C439: 0.4 | D439: 0.4
A440: 44687 | B440: Medium | C440: 0.4 | D440: 0.3
A441: 44715 | B441: Medium | C441: 0.4 | D441: 0.3
A442: 44750 | B442: Medium | C442: 0.3 | D442: 0.3
A443: 44778 | B443: Medium | C443: 0.3 | D443: 0.5
A444: 44806 | B444: Medium | C444: 0.4 | D444: 0.3
A445: 44841 | B445: Medium | C445: 0.3 | D445: 0.3
A446: 44869 | B446: Medium | C446: 0.3 | D446: 0.4
... A490: 46241 | B490: Medium | C490: 0.3 | D490: 0.1
A491: Average Hourly Earnings YoY (55 events)
A492: Date | B492: Impact | C492: Forecast | D492: Actual
A493: 44533 | B493: Medium | C493: 5 | D493: 4.8
A494: 44568 | B494: Medium | C494: 4.2 | D494: 4.7
A495: 44596 | B495: Medium | C495: 5.2 | D495: 5.7
A496: 44624 | B496: Medium | C496: 5.8 | D496: 5.1
A497: 44652 | B497: Medium | C497: 5.5 | D497: 5.6
A498: 44687 | B498: Medium | C498: 5.5 | D498: 5.5
A499: 44715 | B499: Medium | C499: 5.2 | D499: 5.2
A500: 44750 | B500: Medium | C500: 5 | D500: 5.1
A501: 44778 | B501: Medium | C501: 4.9 | D501: 5.2
A502: 44806 | B502: Medium | C502: 5.3 | D502: 5.2
A503: 44841 | B503: Medium | C503: 5.1 | D503: 5
A504: 44869 | B504: Medium | C504: 4.7 | D504: 4.7
... A547: 46241 | B547: Medium | C547: 3.5 | D547: 3.2
A548: Balance of Trade (140 events)
A549: Date | B549: Impact | C549: Forecast | D549: Actual
A550: 42011 | B550: High | C550: -42 | D550: -39
A551: 42040 | B551: High | C551: -38 | D551: -46.56
A552: 42069 | B552: High | C552: -41.6 | D552: -41.8
A553: 42096 | B553: High | C553: -41.2 | D553: -35.44
A554: 42129 | B554: High | C554: -40.3 | D554: -51.37
A555: 42158 | B555: High | C555: -44 | D555: -40.88
A556: 42192 | B556: High | C556: -42.6 | D556: -41.87
A557: 42221 | B557: High | C557: -42.8 | D557: -43.84
A558: 42250 | B558: High | C558: -42.4 | D558: -41.86
A559: 42283 | B559: High | C559: -47.4 | D559: -48.33
A560: 42312 | B560: High | C560: -41.1 | D560: -40.81
A561: 42342 | B561: High | C561: -40.5 | D561: -43.89
... A689: 46238 | B689: Medium | C689: -73 | D689: -73.3
A690: Building Permits (94 events)
A691: Date | B691: Impact | C691: Forecast | D691: Actual
A692: 42025 | B692: Medium | C692: 1055 | D692: 1032
A693: 42053 | B693: Medium | C693: 1068 | D693: 1053
A694: 42080 | B694: Medium | C694: 1065 | D694: 1092
A695: 42110 | B695: Medium | C695: 1080 | D695: 1039
A696: 42143 | B696: Medium | C696: 1065 | D696: 1143
A697: 42171 | B697: Medium | C697: 1100 | D697: 1275
A698: 42202 | B698: Medium | C698: 1150 | D698: 1343
A699: 42234 | B699: Medium | C699: 1232 | D699: 1119
A700: 42264 | B700: Medium | C700: 1160 | D700: 1170
A701: 42297 | B701: Medium | C701: 1164 | D701: 1103
A702: 42326 | B702: Medium | C702: 1150 | D702: 1150
A703: 42354 | B703: Medium | C703: 1150 | D703: 1289
... A785: 44853 | B785: High | C785: 1.53 | D785: 1.564
A786: Building Permits Final (1 events)
A787: Date | B787: Impact | C787: Forecast | D787: Actual
A788: 44888 | B788: Medium | C788: 1.526 | D788: 1.512
A789: Building Permits MoM (36 events)
A790: Date | B790: Impact | C790: Forecast | D790: Actual
A791: 42570 | B791: Medium | C791: 0.6 | D791: 1.5
A792: 42598 | B792: Medium | C792: 0.6 | D792: -0.1
A793: 42633 | B793: Medium | C793: 2.5 | D793: -0.4
...

Sheet Z-Score Calc
A1: Z-Score Calc — live Excel formulas for every row (min_periods=20, std floored at 1e-12, z clipped to +/-8, trigger |z| >= 0.5, direction = sign(z)). | M1: z parameters (from fx_strict_battery.py)
A2: Stats use only rows ABOVE the current row within the same title block (no lookahead, mirrors pandas expanding(...).shift(1)). Rows 1-20 of each block have no z (insufficient history). | M2: min prior events | N2: 20
M3: std floor | N3: 1e-12
A4: ADP Employment Change (137 events) | M4: z clip | N4: +-8.0
A5: Date | B5: Impact | C5: Forecast | D5: Actual | E5: Surprise | F5: Prior | G5: Trail mean | H5: Trail std | I5: z | J5: Trigger | K5: Direction | M5: trigger |z| >= | N5: 0.5
A6: 42011 | B6: Medium | C6: 226 | D6: 241 | E6: =D6-C6 | F6: =ROW()-ROW($A$6) | M6: stats window | N6: expanding, prior rows only (shift(1))
A7: 42039 | B7: Medium | C7: 225 | D7: 213 | E7: =D7-C7 | F7: =ROW()-ROW($A$6) | M7: 1-pip RT cost (frac) | N7: 7.9464792e-05
A8: 42067 | B8: Medium | C8: 220 | D8: 212 | E8: =D8-C8 | F8: =ROW()-ROW($A$6)
A9: 42095 | B9: Medium | C9: 225 | D9: 189 | E9: =D9-C9 | F9: =ROW()-ROW($A$6)
A10: 42130 | B10: Medium | C10: 200 | D10: 169 | E10: =D10-C10 | F10: =ROW()-ROW($A$6)
A11: 42158 | B11: Medium | C11: 200 | D11: 201 | E11: =D11-C11 | F11: =ROW()-ROW($A$6)
A12: 42186 | B12: Medium | C12: 218 | D12: 237 | E12: =D12-C12 | F12: =ROW()-ROW($A$6)
A13: 42221 | B13: Medium | C13: 215 | D13: 185 | E13: =D13-C13 | F13: =ROW()-ROW($A$6)
A14: 42249 | B14: Medium | C14: 201 | D14: 190 | E14: =D14-C14 | F14: =ROW()-ROW($A$6)
A15: 42277 | B15: Medium | C15: 194 | D15: 200 | E15: =D15-C15 | F15: =ROW()-ROW($A$6)
A16: 42312 | B16: Medium | C16: 180 | D16: 182 | E16: =D16-C16 | F16: =ROW()-ROW($A$6)
A17: 42340 | B17: Medium | C17: 190 | D17: 217 | E17: =D17-C17 | F17: =ROW()-ROW($A$6)
A18: 42375 | B18: Medium | C18: 192 | D18: 257 | E18: =D18-C18 | F18: =ROW()-ROW($A$6)
A19: 42403 | B19: Medium | C19: 195 | D19: 205 | E19: =D19-C19 | F19: =ROW()-ROW($A$6)
... A25: 42585 | B25: Medium | C25: 170 | D25: 179 | E25: =D25-C25 | F25: =ROW()-ROW($A$6)
A26: 42613 | B26: Medium | C26: 175 | D26: 177 | E26: =D26-C26 | F26: =ROW()-ROW($A$6) | G26: =AVERAGE($E$6:$E$25) | H26: =STDEV($E$6:$E$25) | I26: =MIN(MAX((E26-G26)/IF(H26>1e-12,H26,NA()),-8.0),8.0) | J26: =IF(NOT(ISNA(I26)),IF(ABS(I26)>=0.5,"TRIGGER",""),"") | K26: =IF(J26="TRIGGER",IF(I26>0,"LONG","SHORT"),"")
A27: 42648 | B27: Medium | C27: 169 | D27: 154 | E27: =D27-C27 | F27: =ROW()-ROW($A$6) | G27: =AVERAGE($E$6:$E$26) | H27: =STDEV($E$6:$E$26) | I27: =MIN(MAX((E27-G27)/IF(H27>1e-12,H27,NA()),-8.0),8.0) | J27: =IF(NOT(ISNA(I27)),IF(ABS(I27)>=0.5,"TRIGGER",""),"") | K27: =IF(J27="TRIGGER",IF(I27>0,"LONG","SHORT"),"")
A28: 42676 | B28: Medium | C28: 165 | D28: 147 | E28: =D28-C28 | F28: =ROW()-ROW($A$6) | G28: =AVERAGE($E$6:$E$27) | H28: =STDEV($E$6:$E$27) | I28: =MIN(MAX((E28-G28)/IF(H28>1e-12,H28,NA()),-8.0),8.0) | J28: =IF(NOT(ISNA(I28)),IF(ABS(I28)>=0.5,"TRIGGER",""),"") | K28: =IF(J28="TRIGGER",IF(I28>0,"LONG","SHORT"),"")
A29: 42704 | B29: Medium | C29: 165 | D29: 216 | E29: =D29-C29 | F29: =ROW()-ROW($A$6) | G29: =AVERAGE($E$6:$E$28) | H29: =STDEV($E$6:$E$28) | I29: =MIN(MAX((E29-G29)/IF(H29>1e-12,H29,NA()),-8.0),8.0) | J29: =IF(NOT(ISNA(I29)),IF(ABS(I29)>=0.5,"TRIGGER",""),"") | K29: =IF(J29="TRIGGER",IF(I29>0,"LONG","SHORT"),"")
A30: 42740 | B30: Medium | C30: 170 | D30: 153 | E30: =D30-C30 | F30: =ROW()-ROW($A$6) | G30: =AVERAGE($E$6:$E$29) | H30: =STDEV($E$6:$E$29) | I30: =MIN(MAX((E30-G30)/IF(H30>1e-12,H30,NA()),-8.0),8.0) | J30: =IF(NOT(ISNA(I30)),IF(ABS(I30)>=0.5,"TRIGGER",""),"") | K30: =IF(J30="TRIGGER",IF(I30>0,"LONG","SHORT"),"")
A31: 42767 | B31: Medium | C31: 165 | D31: 246 | E31: =D31-C31 | F31: =ROW()-ROW($A$6) | G31: =AVERAGE($E$6:$E$30) | H31: =STDEV($E$6:$E$30) | I31: =MIN(MAX((E31-G31)/IF(H31>1e-12,H31,NA()),-8.0),8.0) | J31: =IF(NOT(ISNA(I31)),IF(ABS(I31)>=0.5,"TRIGGER",""),"") | K31: =IF(J31="TRIGGER",IF(I31>0,"LONG","SHORT"),"")
A32: 42802 | B32: Medium | C32: 190 | D32: 298 | E32: =D32-C32 | F32: =ROW()-ROW($A$6) | G32: =AVERAGE($E$6:$E$31) | H32: =STDEV($E$6:$E$31) | I32: =MIN(MAX((E32-G32)/IF(H32>1e-12,H32,NA()),-8.0),8.0) | J32: =IF(NOT(ISNA(I32)),IF(ABS(I32)>=0.5,"TRIGGER",""),"") | K32: =IF(J32="TRIGGER",IF(I32>0,"LONG","SHORT"),"")
A33: 42830 | B33: Medium | C33: 187 | D33: 263 | E33: =D33-C33 | F33: =ROW()-ROW($A$6) | G33: =AVERAGE($E$6:$E$32) | H33: =STDEV($E$6:$E$32) | I33: =MIN(MAX((E33-G33)/IF(H33>1e-12,H33,NA()),-8.0),8.0) | J33: =IF(NOT(ISNA(I33)),IF(ABS(I33)>=0.5,"TRIGGER",""),"") | K33: =IF(J33="TRIGGER",IF(I33>0,"LONG","SHORT"),"")
A34: 42858 | B34: Medium | C34: 175 | D34: 177 | E34: =D34-C34 | F34: =ROW()-ROW($A$6) | G34: =AVERAGE($E$6:$E$33) | H34: =STDEV($E$6:$E$33) | I34: =MIN(MAX((E34-G34)/IF(H34>1e-12,H34,NA()),-8.0),8.0) | J34: =IF(NOT(ISNA(I34)),IF(ABS(I34)>=0.5,"TRIGGER",""),"") | K34: =IF(J34="TRIGGER",IF(I34>0,"LONG","SHORT"),"")
A35: 42887 | B35: Medium | C35: 185 | D35: 253 | E35: =D35-C35 | F35: =ROW()-ROW($A$6) | G35: =AVERAGE($E$6:$E$34) | H35: =STDEV($E$6:$E$34) | I35: =MIN(MAX((E35-G35)/IF(H35>1e-12,H35,NA()),-8.0),8.0) | J35: =IF(NOT(ISNA(I35)),IF(ABS(I35)>=0.5,"TRIGGER",""),"") | K35: =IF(J35="TRIGGER",IF(I35>0,"LONG","SHORT"),"")
A36: 42922 | B36: Medium | C36: 185 | D36: 158 | E36: =D36-C36 | F36: =ROW()-ROW($A$6) | G36: =AVERAGE($E$6:$E$35) | H36: =STDEV($E$6:$E$35) | I36: =MIN(MAX((E36-G36)/IF(H36>1e-12,H36,NA()),-8.0),8.0) | J36: =IF(NOT(ISNA(I36)),IF(ABS(I36)>=0.5,"TRIGGER",""),"") | K36: =IF(J36="TRIGGER",IF(I36>0,"LONG","SHORT"),"")
A37: 42949 | B37: Medium | C37: 185 | D37: 178 | E37: =D37-C37 | F37: =ROW()-ROW($A$6) | G37: =AVERAGE($E$6:$E$36) | H37: =STDEV($E$6:$E$36) | I37: =MIN(MAX((E37-G37)/IF(H37>1e-12,H37,NA()),-8.0),8.0) | J37: =IF(NOT(ISNA(I37)),IF(ABS(I37)>=0.5,"TRIGGER",""),"") | K37: =IF(J37="TRIGGER",IF(I37>0,"LONG","SHORT"),"")
A38: 42977 | B38: Medium | C38: 183 | D38: 237 | E38: =D38-C38 | F38: =ROW()-ROW($A$6) | G38: =AVERAGE($E$6:$E$37) | H38: =STDEV($E$6:$E$37) | I38: =MIN(MAX((E38-G38)/IF(H38>1e-12,H38,NA()),-8.0),8.0) | J38: =IF(NOT(ISNA(I38)),IF(ABS(I38)>=0.5,"TRIGGER",""),"") | K38: =IF(J38="TRIGGER",IF(I38>0,"LONG","SHORT"),"")
A39: 43012 | B39: Medium | C39: 125 | D39: 135 | E39: =D39-C39 | F39: =ROW()-ROW($A$6) | G39: =AVERAGE($E$6:$E$38) | H39: =STDEV($E$6:$E$38) | I39: =MIN(MAX((E39-G39)/IF(H39>1e-12,H39,NA()),-8.0),8.0) | J39: =IF(NOT(ISNA(I39)),IF(ABS(I39)>=0.5,"TRIGGER",""),"") | K39: =IF(J39="TRIGGER",IF(I39>0,"LONG","SHORT"),"")
A40: 43040 | B40: Medium | C40: 200 | D40: 235 | E40: =D40-C40 | F40: =ROW()-ROW($A$6) | G40: =AVERAGE($E$6:$E$39) | H40: =STDEV($E$6:$E$39) | I40: =MIN(MAX((E40-G40)/IF(H40>1e-12,H40,NA()),-8.0),8.0) | J40: =IF(NOT(ISNA(I40)),IF(ABS(I40)>=0.5,"TRIGGER",""),"") | K40: =IF(J40="TRIGGER",IF(I40>0,"LONG","SHORT"),"")
A41: 43075 | B41: Medium | C41: 185 | D41: 190 | E41: =D41-C41 | F41: =ROW()-ROW($A$6) | G41: =AVERAGE($E$6:$E$40) | H41: =STDEV($E$6:$E$40) | I41: =MIN(MAX((E41-G41)/IF(H41>1e-12,H41,NA()),-8.0),8.0) | J41: =IF(NOT(ISNA(I41)),IF(ABS(I41)>=0.5,"TRIGGER",""),"") | K41: =IF(J41="TRIGGER",IF(I41>0,"LONG","SHORT"),"")
A42: 43104 | B42: Medium | C42: 190 | D42: 250 | E42: =D42-C42 | F42: =ROW()-ROW($A$6) | G42: =AVERAGE($E$6:$E$41) | H42: =STDEV($E$6:$E$41) | I42: =MIN(MAX((E42-G42)/IF(H42>1e-12,H42,NA()),-8.0),8.0) | J42: =IF(NOT(ISNA(I42)),IF(ABS(I42)>=0.5,"TRIGGER",""),"") | K42: =IF(J42="TRIGGER",IF(I42>0,"LONG","SHORT"),"")
A43: 43131 | B43: Medium | C43: 186 | D43: 234 | E43: =D43-C43 | F43: =ROW()-ROW($A$6) | G43: =AVERAGE($E$6:$E$42) | H43: =STDEV($E$6:$E$42) | I43: =MIN(MAX((E43-G43)/IF(H43>1e-12,H43,NA()),-8.0),8.0) | J43: =IF(NOT(ISNA(I43)),IF(ABS(I43)>=0.5,"TRIGGER",""),"") | K43: =IF(J43="TRIGGER",IF(I43>0,"LONG","SHORT"),"")
A44: 43166 | B44: Medium | C44: 195 | D44: 235 | E44: =D44-C44 | F44: =ROW()-ROW($A$6) | G44: =AVERAGE($E$6:$E$43) | H44: =STDEV($E$6:$E$43) | I44: =MIN(MAX((E44-G44)/IF(H44>1e-12,H44,NA()),-8.0),8.0) | J44: =IF(NOT(ISNA(I44)),IF(ABS(I44)>=0.5,"TRIGGER",""),"") | K44: =IF(J44="TRIGGER",IF(I44>0,"LONG","SHORT"),"")
A45: 43194 | B45: Medium | C45: 208 | D45: 241 | E45: =D45-C45 | F45: =ROW()-ROW($A$6) | G45: =AVERAGE($E$6:$E$44) | H45: =STDEV($E$6:$E$44) | I45: =MIN(MAX((E45-G45)/IF(H45>1e-12,H45,NA()),-8.0),8.0) | J45: =IF(NOT(ISNA(I45)),IF(ABS(I45)>=0.5,"TRIGGER",""),"") | K45: =IF(J45="TRIGGER",IF(I45>0,"LONG","SHORT"),"")
A46: 43222 | B46: Medium | C46: 200 | D46: 204 | E46: =D46-C46 | F46: =ROW()-ROW($A$6) | G46: =AVERAGE($E$6:$E$45) | H46: =STDEV($E$6:$E$45) | I46: =MIN(MAX((E46-G46)/IF(H46>1e-12,H46,NA()),-8.0),8.0) | J46: =IF(NOT(ISNA(I46)),IF(ABS(I46)>=0.5,"TRIGGER",""),"") | K46: =IF(J46="TRIGGER",IF(I46>0,"LONG","SHORT"),"")
A47: 43250 | B47: Medium | C47: 190 | D47: 178 | E47: =D47-C47 | F47: =ROW()-ROW($A$6) | G47: =AVERAGE($E$6:$E$46) | H47: =STDEV($E$6:$E$46) | I47: =MIN(MAX((E47-G47)/IF(H47>1e-12,H47,NA()),-8.0),8.0) | J47: =IF(NOT(ISNA(I47)),IF(ABS(I47)>=0.5,"TRIGGER",""),"") | K47: =IF(J47="TRIGGER",IF(I47>0,"LONG","SHORT"),"")
A48: 43286 | B48: Medium | C48: 150 | D48: 177 | E48: =D48-C48 | F48: =ROW()-ROW($A$6) | G48: =AVERAGE($E$6:$E$47) | H48: =STDEV($E$6:$E$47) | I48: =MIN(MAX((E48-G48)/IF(H48>1e-12,H48,NA()),-8.0),8.0) | J48: =IF(NOT(ISNA(I48)),IF(ABS(I48)>=0.5,"TRIGGER",""),"") | K48: =IF(J48="TRIGGER",IF(I48>0,"LONG","SHORT"),"")
A49: 43313 | B49: Medium | C49: 185 | D49: 219 | E49: =D49-C49 | F49: =ROW()-ROW($A$6) | G49: =AVERAGE($E$6:$E$48) | H49: =STDEV($E$6:$E$48) | I49: =MIN(MAX((E49-G49)/IF(H49>1e-12,H49,NA()),-8.0),8.0) | J49: =IF(NOT(ISNA(I49)),IF(ABS(I49)>=0.5,"TRIGGER",""),"") | K49: =IF(J49="TRIGGER",IF(I49>0,"LONG","SHORT"),"")
A50: 43349 | B50: Medium | C50: 190 | D50: 163 | E50: =D50-C50 | F50: =ROW()-ROW($A$6) | G50: =AVERAGE($E$6:$E$49) | H50: =STDEV($E$6:$E$49) | I50: =MIN(MAX((E50-G50)/IF(H50>1e-12,H50,NA()),-8.0),8.0) | J50: =IF(NOT(ISNA(I50)),IF(ABS(I50)>=0.5,"TRIGGER",""),"") | K50: =IF(J50="TRIGGER",IF(I50>0,"LONG","SHORT"),"")
A51: 43376 | B51: Medium | C51: 185 | D51: 230 | E51: =D51-C51 | F51: =ROW()-ROW($A$6) | G51: =AVERAGE($E$6:$E$50) | H51: =STDEV($E$6:$E$50) | I51: =MIN(MAX((E51-G51)/IF(H51>1e-12,H51,NA()),-8.0),8.0) | J51: =IF(NOT(ISNA(I51)),IF(ABS(I51)>=0.5,"TRIGGER",""),"") | K51: =IF(J51="TRIGGER",IF(I51>0,"LONG","SHORT"),"")
A52: 43404 | B52: Medium | C52: 189 | D52: 227 | E52: =D52-C52 | F52: =ROW()-ROW($A$6) | G52: =AVERAGE($E$6:$E$51) | H52: =STDEV($E$6:$E$51) | I52: =MIN(MAX((E52-G52)/IF(H52>1e-12,H52,NA()),-8.0),8.0) | J52: =IF(NOT(ISNA(I52)),IF(ABS(I52)>=0.5,"TRIGGER",""),"") | K52: =IF(J52="TRIGGER",IF(I52>0,"LONG","SHORT"),"")
A53: 43440 | B53: Medium | C53: 195 | D53: 179 | E53: =D53-C53 | F53: =ROW()-ROW($A$6) | G53: =AVERAGE($E$6:$E$52) | H53: =STDEV($E$6:$E$52) | I53: =MIN(MAX((E53-G53)/IF(H53>1e-12,H53,NA()),-8.0),8.0) | J53: =IF(NOT(ISNA(I53)),IF(ABS(I53)>=0.5,"TRIGGER",""),"") | K53: =IF(J53="TRIGGER",IF(I53>0,"LONG","SHORT"),"")
A54: 43468 | B54: Medium | C54: 178 | D54: 271 | E54: =D54-C54 | F54: =ROW()-ROW($A$6) | G54: =AVERAGE($E$6:$E$53) | H54: =STDEV($E$6:$E$53) | I54: =MIN(MAX((E54-G54)/IF(H54>1e-12,H54,NA()),-8.0),8.0) | J54: =IF(NOT(ISNA(I54)),IF(ABS(I54)>=0.5,"TRIGGER",""),"") | K54: =IF(J54="TRIGGER",IF(I54>0,"LONG","SHORT"),"")
A55: 43495 | B55: Medium | C55: 178 | D55: 213 | E55: =D55-C55 | F55: =ROW()-ROW($A$6) | G55: =AVERAGE($E$6:$E$54) | H55: =STDEV($E$6:$E$54) | I55: =MIN(MAX((E55-G55)/IF(H55>1e-12,H55,NA()),-8.0),8.0) | J55: =IF(NOT(ISNA(I55)),IF(ABS(I55)>=0.5,"TRIGGER",""),"") | K55: =IF(J55="TRIGGER",IF(I55>0,"LONG","SHORT"),"")
A56: 43530 | B56: Medium | C56: 189 | D56: 183 | E56: =D56-C56 | F56: =ROW()-ROW($A$6) | G56: =AVERAGE($E$6:$E$55) | H56: =STDEV($E$6:$E$55) | I56: =MIN(MAX((E56-G56)/IF(H56>1e-12,H56,NA()),-8.0),8.0) | J56: =IF(NOT(ISNA(I56)),IF(ABS(I56)>=0.5,"TRIGGER",""),"") | K56: =IF(J56="TRIGGER",IF(I56>0,"LONG","SHORT"),"")
A57: 43558 | B57: Medium | C57: 170 | D57: 129 | E57: =D57-C57 | F57: =ROW()-ROW($A$6) | G57: =AVERAGE($E$6:$E$56) | H57: =STDEV($E$6:$E$56) | I57: =MIN(MAX((E57-G57)/IF(H57>1e-12,H57,NA()),-8.0),8.0) | J57: =IF(NOT(ISNA(I57)),IF(ABS(I57)>=0.5,"TRIGGER",""),"") | K57: =IF(J57="TRIGGER",IF(I57>0,"LONG","SHORT"),"")
A58: 43586 | B58: Medium | C58: 180 | D58: 275 | E58: =D58-C58 | F58: =ROW()-ROW($A$6) | G58: =AVERAGE($E$6:$E$57) | H58: =STDEV($E$6:$E$57) | I58: =MIN(MAX((E58-G58)/IF(H58>1e-12,H58,NA()),-8.0),8.0) | J58: =IF(NOT(ISNA(I58)),IF(ABS(I58)>=0.5,"TRIGGER",""),"") | K58: =IF(J58="TRIGGER",IF(I58>0,"LONG","SHORT"),"")
A59: 43621 | B59: Medium | C59: 180 | D59: 27 | E59: =D59-C59 | F59: =ROW()-ROW($A$6) | G59: =AVERAGE($E$6:$E$58) | H59: =STDEV($E$6:$E$58) | I59: =MIN(MAX((E59-G59)/IF(H59>1e-12,H59,NA()),-8.0),8.0) | J59: =IF(NOT(ISNA(I59)),IF(ABS(I59)>=0.5,"TRIGGER",""),"") | K59: =IF(J59="TRIGGER",IF(I59>0,"LONG","SHORT"),"")
A60: 43649 | B60: Medium | C60: 140 | D60: 102 | E60: =D60-C60 | F60: =ROW()-ROW($A$6) | G60: =AVERAGE($E$6:$E$59) | H60: =STDEV($E$6:$E$59) | I60: =MIN(MAX((E60-G60)/IF(H60>1e-12,H60,NA()),-8.0),8.0) | J60: =IF(NOT(ISNA(I60)),IF(ABS(I60)>=0.5,"TRIGGER",""),"") | K60: =IF(J60="TRIGGER",IF(I60>0,"LONG","SHORT"),"")
A61: 43677 | B61: Medium | C61: 150 | D61: 156 | E61: =D61-C61 | F61: =ROW()-ROW($A$6) | G61: =AVERAGE($E$6:$E$60) | H61: =STDEV($E$6:$E$60) | I61: =MIN(MAX((E61-G61)/IF(H61>1e-12,H61,NA()),-8.0),8.0) | J61: =IF(NOT(ISNA(I61)),IF(ABS(I61)>=0.5,"TRIGGER",""),"") | K61: =IF(J61="TRIGGER",IF(I61>0,"LONG","SHORT"),"")
A62: 43713 | B62: Medium | C62: 149 | D62: 195 | E62: =D62-C62 | F62: =ROW()-ROW($A$6) | G62: =AVERAGE($E$6:$E$61) | H62: =STDEV($E$6:$E$61) | I62: =MIN(MAX((E62-G62)/IF(H62>1e-12,H62,NA()),-8.0),8.0) | J62: =IF(NOT(ISNA(I62)),IF(ABS(I62)>=0.5,"TRIGGER",""),"") | K62: =IF(J62="TRIGGER",IF(I62>0,"LONG","SHORT"),"")
A63: 43740 | B63: Medium | C63: 140 | D63: 135 | E63: =D63-C63 | F63: =ROW()-ROW($A$6) | G63: =AVERAGE($E$6:$E$62) | H63: =STDEV($E$6:$E$62) | I63: =MIN(MAX((E63-G63)/IF(H63>1e-12,H63,NA()),-8.0),8.0) | J63: =IF(NOT(ISNA(I63)),IF(ABS(I63)>=0.5,"TRIGGER",""),"") | K63: =IF(J63="TRIGGER",IF(I63>0,"LONG","SHORT"),"")
A64: 43768 | B64: Medium | C64: 120 | D64: 125 | E64: =D64-C64 | F64: =ROW()-ROW($A$6) | G64: =AVERAGE($E$6:$E$63) | H64: =STDEV($E$6:$E$63) | I64: =MIN(MAX((E64-G64)/IF(H64>1e-12,H64,NA()),-8.0),8.0) | J64: =IF(NOT(ISNA(I64)),IF(ABS(I64)>=0.5,"TRIGGER",""),"") | K64: =IF(J64="TRIGGER",IF(I64>0,"LONG","SHORT"),"")
A65: 43803 | B65: Medium | C65: 140 | D65: 67 | E65: =D65-C65 | F65: =ROW()-ROW($A$6) | G65: =AVERAGE($E$6:$E$64) | H65: =STDEV($E$6:$E$64) | I65: =MIN(MAX((E65-G65)/IF(H65>1e-12,H65,NA()),-8.0),8.0) | J65: =IF(NOT(ISNA(I65)),IF(ABS(I65)>=0.5,"TRIGGER",""),"") | K65: =IF(J65="TRIGGER",IF(I65>0,"LONG","SHORT"),"")
A66: 43838 | B66: Medium | C66: 160 | D66: 202 | E66: =D66-C66 | F66: =ROW()-ROW($A$6) | G66: =AVERAGE($E$6:$E$65) | H66: =STDEV($E$6:$E$65) | I66: =MIN(MAX((E66-G66)/IF(H66>1e-12,H66,NA()),-8.0),8.0) | J66: =IF(NOT(ISNA(I66)),IF(ABS(I66)>=0.5,"TRIGGER",""),"") | K66: =IF(J66="TRIGGER",IF(I66>0,"LONG","SHORT"),"")
A67: 43866 | B67: Medium | C67: 156 | D67: 291 | E67: =D67-C67 | F67: =ROW()-ROW($A$6) | G67: =AVERAGE($E$6:$E$66) | H67: =STDEV($E$6:$E$66) | I67: =MIN(MAX((E67-G67)/IF(H67>1e-12,H67,NA()),-8.0),8.0) | J67: =IF(NOT(ISNA(I67)),IF(ABS(I67)>=0.5,"TRIGGER",""),"") | K67: =IF(J67="TRIGGER",IF(I67>0,"LONG","SHORT"),"")
A68: 43894 | B68: Medium | C68: 170 | D68: 183 | E68: =D68-C68 | F68: =ROW()-ROW($A$6) | G68: =AVERAGE($E$6:$E$67) | H68: =STDEV($E$6:$E$67) | I68: =MIN(MAX((E68-G68)/IF(H68>1e-12,H68,NA()),-8.0),8.0) | J68: =IF(NOT(ISNA(I68)),IF(ABS(I68)>=0.5,"TRIGGER",""),"") | K68: =IF(J68="TRIGGER",IF(I68>0,"LONG","SHORT"),"")
A69: 43922 | B69: Medium | C69: -150 | D69: -27 | E69: =D69-C69 | F69: =ROW()-ROW($A$6) | G69: =AVERAGE($E$6:$E$68) | H69: =STDEV($E$6:$E$68) | I69: =MIN(MAX((E69-G69)/IF(H69>1e-12,H69,NA()),-8.0),8.0) | J69: =IF(NOT(ISNA(I69)),IF(ABS(I69)>=0.5,"TRIGGER",""),"") | K69: =IF(J69="TRIGGER",IF(I69>0,"LONG","SHORT"),"")
A70: 43957 | B70: Medium | C70: -20000 | D70: -20236 | E70: =D70-C70 | F70: =ROW()-ROW($A$6) | G70: =AVERAGE($E$6:$E$69) | H70: =STDEV($E$6:$E$69) | I70: =MIN(MAX((E70-G70)/IF(H70>1e-12,H70,NA()),-8.0),8.0) | J70: =IF(NOT(ISNA(I70)),IF(ABS(I70)>=0.5,"TRIGGER",""),"") | K70: =IF(J70="TRIGGER",IF(I70>0,"LONG","SHORT"),"")
A71: 43985 | B71: Medium | C71: -9000 | D71: -2760 | E71: =D71-C71 | F71: =ROW()-ROW($A$6) | G71: =AVERAGE($E$6:$E$70) | H71: =STDEV($E$6:$E$70) | I71: =MIN(MAX((E71-G71)/IF(H71>1e-12,H71,NA()),-8.0),8.0) | J71: =IF(NOT(ISNA(I71)),IF(ABS(I71)>=0.5,"TRIGGER",""),"") | K71: =IF(J71="TRIGGER",IF(I71>0,"LONG","SHORT"),"")
A72: 44013 | B72: Medium | C72: 3000 | D72: 2369 | E72: =D72-C72 | F72: =ROW()-ROW($A$6) | G72: =AVERAGE($E$6:$E$71) | H72: =STDEV($E$6:$E$71) | I72: =MIN(MAX((E72-G72)/IF(H72>1e-12,H72,NA()),-8.0),8.0) | J72: =IF(NOT(ISNA(I72)),IF(ABS(I72)>=0.5,"TRIGGER",""),"") | K72: =IF(J72="TRIGGER",IF(I72>0,"LONG","SHORT"),"")
A73: 44048 | B73: Medium | C73: 1500 | D73: 167 | E73: =D73-C73 | F73: =ROW()-ROW($A$6) | G73: =AVERAGE($E$6:$E$72) | H73: =STDEV($E$6:$E$72) | I73: =MIN(MAX((E73-G73)/IF(H73>1e-12,H73,NA()),-8.0),8.0) | J73: =IF(NOT(ISNA(I73)),IF(ABS(I73)>=0.5,"TRIGGER",""),"") | K73: =IF(J73="TRIGGER",IF(I73>0,"LONG","SHORT"),"")
A74: 44076 | B74: Medium | C74: 950 | D74: 428 | E74: =D74-C74 | F74: =ROW()-ROW($A$6) | G74: =AVERAGE($E$6:$E$73) | H74: =STDEV($E$6:$E$73) | I74: =MIN(MAX((E74-G74)/IF(H74>1e-12,H74,NA()),-8.0),8.0) | J74: =IF(NOT(ISNA(I74)),IF(ABS(I74)>=0.5,"TRIGGER",""),"") | K74: =IF(J74="TRIGGER",IF(I74>0,"LONG","SHORT"),"")
A75: 44104 | B75: Medium | C75: 650 | D75: 749 | E75: =D75-C75 | F75: =ROW()-ROW($A$6) | G75: =AVERAGE($E$6:$E$74) | H75: =STDEV($E$6:$E$74) | I75: =MIN(MAX((E75-G75)/IF(H75>1e-12,H75,NA()),-8.0),8.0) | J75: =IF(NOT(ISNA(I75)),IF(ABS(I75)>=0.5,"TRIGGER",""),"") | K75: =IF(J75="TRIGGER",IF(I75>0,"LONG","SHORT"),"")
A76: 44139 | B76: Medium | C76: 650 | D76: 365 | E76: =D76-C76 | F76: =ROW()-ROW($A$6) | G76: =AVERAGE($E$6:$E$75) | H76: =STDEV($E$6:$E$75) | I76: =MIN(MAX((E76-G76)/IF(H76>1e-12,H76,NA()),-8.0),8.0) | J76: =IF(NOT(ISNA(I76)),IF(ABS(I76)>=0.5,"TRIGGER",""),"") | K76: =IF(J76="TRIGGER",IF(I76>0,"LONG","SHORT"),"")
A77: 44167 | B77: Medium | C77: 410 | D77: 307 | E77: =D77-C77 | F77: =ROW()-ROW($A$6) | G77: =AVERAGE($E$6:$E$76) | H77: =STDEV($E$6:$E$76) | I77: =MIN(MAX((E77-G77)/IF(H77>1e-12,H77,NA()),-8.0),8.0) | J77: =IF(NOT(ISNA(I77)),IF(ABS(I77)>=0.5,"TRIGGER",""),"") | K77: =IF(J77="TRIGGER",IF(I77>0,"LONG","SHORT"),"")
A78: 44202 | B78: Medium | C78: 88 | D78: -123 | E78: =D78-C78 | F78: =ROW()-ROW($A$6) | G78: =AVERAGE($E$6:$E$77) | H78: =STDEV($E$6:$E$77) | I78: =MIN(MAX((E78-G78)/IF(H78>1e-12,H78,NA()),-8.0),8.0) | J78: =IF(NOT(ISNA(I78)),IF(ABS(I78)>=0.5,"TRIGGER",""),"") | K78: =IF(J78="TRIGGER",IF(I78>0,"LONG","SHORT"),"")
A79: 44230 | B79: Medium | C79: 49 | D79: 174 | E79: =D79-C79 | F79: =ROW()-ROW($A$6) | G79: =AVERAGE($E$6:$E$78) | H79: =STDEV($E$6:$E$78) | I79: =MIN(MAX((E79-G79)/IF(H79>1e-12,H79,NA()),-8.0),8.0) | J79: =IF(NOT(ISNA(I79)),IF(ABS(I79)>=0.5,"TRIGGER",""),"") | K79: =IF(J79="TRIGGER",IF(I79>0,"LONG","SHORT"),"")
A80: 44258 | B80: Medium | C80: 177 | D80: 117 | E80: =D80-C80 | F80: =ROW()-ROW($A$6) | G80: =AVERAGE($E$6:$E$79) | H80: =STDEV($E$6:$E$79) | I80: =MIN(MAX((E80-G80)/IF(H80>1e-12,H80,NA()),-8.0),8.0) | J80: =IF(NOT(ISNA(I80)),IF(ABS(I80)>=0.5,"TRIGGER",""),"") | K80: =IF(J80="TRIGGER",IF(I80>0,"LONG","SHORT"),"")
A81: 44286 | B81: Medium | C81: 550 | D81: 517 | E81: =D81-C81 | F81: =ROW()-ROW($A$6) | G81: =AVERAGE($E$6:$E$80) | H81: =STDEV($E$6:$E$80) | I81: =MIN(MAX((E81-G81)/IF(H81>1e-12,H81,NA()),-8.0),8.0) | J81: =IF(NOT(ISNA(I81)),IF(ABS(I81)>=0.5,"TRIGGER",""),"") | K81: =IF(J81="TRIGGER",IF(I81>0,"LONG","SHORT"),"")
A82: 44321 | B82: Medium | C82: 800 | D82: 742 | E82: =D82-C82 | F82: =ROW()-ROW($A$6) | G82: =AVERAGE($E$6:$E$81) | H82: =STDEV($E$6:$E$81) | I82: =MIN(MAX((E82-G82)/IF(H82>1e-12,H82,NA()),-8.0),8.0) | J82: =IF(NOT(ISNA(I82)),IF(ABS(I82)>=0.5,"TRIGGER",""),"") | K82: =IF(J82="TRIGGER",IF(I82>0,"LONG","SHORT"),"")
A83: 44350 | B83: Medium | C83: 650 | D83: 978 | E83: =D83-C83 | F83: =ROW()-ROW($A$6) | G83: =AVERAGE($E$6:$E$82) | H83: =STDEV($E$6:$E$82) | I83: =MIN(MAX((E83-G83)/IF(H83>1e-12,H83,NA()),-8.0),8.0) | J83: =IF(NOT(ISNA(I83)),IF(ABS(I83)>=0.5,"TRIGGER",""),"") | K83: =IF(J83="TRIGGER",IF(I83>0,"LONG","SHORT"),"")
A84: 44377 | B84: Medium | C84: 600 | D84: 692 | E84: =D84-C84 | F84: =ROW()-ROW($A$6) | G84: =AVERAGE($E$6:$E$83) | H84: =STDEV($E$6:$E$83) | I84: =MIN(MAX((E84-G84)/IF(H84>1e-12,H84,NA()),-8.0),8.0) | J84: =IF(NOT(ISNA(I84)),IF(ABS(I84)>=0.5,"TRIGGER",""),"") | K84: =IF(J84="TRIGGER",IF(I84>0,"LONG","SHORT"),"")
A85: 44412 | B85: Medium | C85: 695 | D85: 330 | E85: =D85-C85 | F85: =ROW()-ROW($A$6) | G85: =AVERAGE($E$6:$E$84) | H85: =STDEV($E$6:$E$84) | I85: =MIN(MAX((E85-G85)/IF(H85>1e-12,H85,NA()),-8.0),8.0) | J85: =IF(NOT(ISNA(I85)),IF(ABS(I85)>=0.5,"TRIGGER",""),"") | K85: =IF(J85="TRIGGER",IF(I85>0,"LONG","SHORT"),"")
A86: 44440 | B86: Medium | C86: 613 | D86: 374 | E86: =D86-C86 | F86: =ROW()-ROW($A$6) | G86: =AVERAGE($E$6:$E$85) | H86: =STDEV($E$6:$E$85) | I86: =MIN(MAX((E86-G86)/IF(H86>1e-12,H86,NA()),-8.0),8.0) | J86: =IF(NOT(ISNA(I86)),IF(ABS(I86)>=0.5,"TRIGGER",""),"") | K86: =IF(J86="TRIGGER",IF(I86>0,"LONG","SHORT"),"")
A87: 44475 | B87: Medium | C87: 428 | D87: 568 | E87: =D87-C87 | F87: =ROW()-ROW($A$6) | G87: =AVERAGE($E$6:$E$86) | H87: =STDEV($E$6:$E$86) | I87: =MIN(MAX((E87-G87)/IF(H87>1e-12,H87,NA()),-8.0),8.0) | J87: =IF(NOT(ISNA(I87)),IF(ABS(I87)>=0.5,"TRIGGER",""),"") | K87: =IF(J87="TRIGGER",IF(I87>0,"LONG","SHORT"),"")
A88: 44503 | B88: Medium | C88: 400 | D88: 571 | E88: =D88-C88 | F88: =ROW()-ROW($A$6) | G88: =AVERAGE($E$6:$E$87) | H88: =STDEV($E$6:$E$87) | I88: =MIN(MAX((E88-G88)/IF(H88>1e-12,H88,NA()),-8.0),8.0) | J88: =IF(NOT(ISNA(I88)),IF(ABS(I88)>=0.5,"TRIGGER",""),"") | K88: =IF(J88="TRIGGER",IF(I88>0,"LONG","SHORT"),"")
A89: 44531 | B89: Medium | C89: 525 | D89: 534 | E89: =D89-C89 | F89: =ROW()-ROW($A$6) | G89: =AVERAGE($E$6:$E$88) | H89: =STDEV($E$6:$E$88) | I89: =MIN(MAX((E89-G89)/IF(H89>1e-12,H89,NA()),-8.0),8.0) | J89: =IF(NOT(ISNA(I89)),IF(ABS(I89)>=0.5,"TRIGGER",""),"") | K89: =IF(J89="TRIGGER",IF(I89>0,"LONG","SHORT"),"")
A90: 44566 | B90: Medium | C90: 400 | D90: 807 | E90: =D90-C90 | F90: =ROW()-ROW($A$6) | G90: =AVERAGE($E$6:$E$89) | H90: =STDEV($E$6:$E$89) | I90: =MIN(MAX((E90-G90)/IF(H90>1e-12,H90,NA()),-8.0),8.0) | J90: =IF(NOT(ISNA(I90)),IF(ABS(I90)>=0.5,"TRIGGER",""),"") | K90: =IF(J90="TRIGGER",IF(I90>0,"LONG","SHORT"),"")
A91: 44594 | B91: Medium | C91: 207 | D91: -301 | E91: =D91-C91 | F91: =ROW()-ROW($A$6) | G91: =AVERAGE($E$6:$E$90) | H91: =STDEV($E$6:$E$90) | I91: =MIN(MAX((E91-G91)/IF(H91>1e-12,H91,NA()),-8.0),8.0) | J91: =IF(NOT(ISNA(I91)),IF(ABS(I91)>=0.5,"TRIGGER",""),"") | K91: =IF(J91="TRIGGER",IF(I91>0,"LONG","SHORT"),"")
A92: 44622 | B92: Medium | C92: 388 | D92: 475 | E92: =D92-C92 | F92: =ROW()-ROW($A$6) | G92: =AVERAGE($E$6:$E$91) | H92: =STDEV($E$6:$E$91) | I92: =MIN(MAX((E92-G92)/IF(H92>1e-12,H92,NA()),-8.0),8.0) | J92: =IF(NOT(ISNA(I92)),IF(ABS(I92)>=0.5,"TRIGGER",""),"") | K92: =IF(J92="TRIGGER",IF(I92>0,"LONG","SHORT"),"")
A93: 44650 | B93: Medium | C93: 450 | D93: 455 | E93: =D93-C93 | F93: =ROW()-ROW($A$6) | G93: =AVERAGE($E$6:$E$92) | H93: =STDEV($E$6:$E$92) | I93: =MIN(MAX((E93-G93)/IF(H93>1e-12,H93,NA()),-8.0),8.0) | J93: =IF(NOT(ISNA(I93)),IF(ABS(I93)>=0.5,"TRIGGER",""),"") | K93: =IF(J93="TRIGGER",IF(I93>0,"LONG","SHORT"),"")
A94: 44685 | B94: Medium | C94: 395 | D94: 247 | E94: =D94-C94 | F94: =ROW()-ROW($A$6) | G94: =AVERAGE($E$6:$E$93) | H94: =STDEV($E$6:$E$93) | I94: =MIN(MAX((E94-G94)/IF(H94>1e-12,H94,NA()),-8.0),8.0) | J94: =IF(NOT(ISNA(I94)),IF(ABS(I94)>=0.5,"TRIGGER",""),"") | K94: =IF(J94="TRIGGER",IF(I94>0,"LONG","SHORT"),"")
A95: 44714 | B95: Medium | C95: 300 | D95: 128 | E95: =D95-C95 | F95: =ROW()-ROW($A$6) | G95: =AVERAGE($E$6:$E$94) | H95: =STDEV($E$6:$E$94) | I95: =MIN(MAX((E95-G95)/IF(H95>1e-12,H95,NA()),-8.0),8.0) | J95: =IF(NOT(ISNA(I95)),IF(ABS(I95)>=0.5,"TRIGGER",""),"") | K95: =IF(J95="TRIGGER",IF(I95>0,"LONG","SHORT"),"")
A96: 44839 | B96: Medium | C96: 200 | D96: 208 | E96: =D96-C96 | F96: =ROW()-ROW($A$6) | G96: =AVERAGE($E$6:$E$95) | H96: =STDEV($E$6:$E$95) | I96: =MIN(MAX((E96-G96)/IF(H96>1e-12,H96,NA()),-8.0),8.0) | J96: =IF(NOT(ISNA(I96)),IF(ABS(I96)>=0.5,"TRIGGER",""),"") | K96: =IF(J96="TRIGGER",IF(I96>0,"LONG","SHORT"),"")
A97: 44867 | B97: Medium | C97: 195 | D97: 239 | E97: =D97-C97 | F97: =ROW()-ROW($A$6) | G97: =AVERAGE($E$6:$E$96) | H97: =STDEV($E$6:$E$96) | I97: =MIN(MAX((E97-G97)/IF(H97>1e-12,H97,NA()),-8.0),8.0) | J97: =IF(NOT(ISNA(I97)),IF(ABS(I97)>=0.5,"TRIGGER",""),"") | K97: =IF(J97="TRIGGER",IF(I97>0,"LONG","SHORT"),"")
A98: 44895 | B98: Medium | C98: 200 | D98: 127 | E98: =D98-C98 | F98: =ROW()-ROW($A$6) | G98: =AVERAGE($E$6:$E$97) | H98: =STDEV($E$6:$E$97) | I98: =MIN(MAX((E98-G98)/IF(H98>1e-12,H98,NA()),-8.0),8.0) | J98: =IF(NOT(ISNA(I98)),IF(ABS(I98)>=0.5,"TRIGGER",""),"") | K98: =IF(J98="TRIGGER",IF(I98>0,"LONG","SHORT"),"")
A99: 44931 | B99: Medium | C99: 150 | D99: 235 | E99: =D99-C99 | F99: =ROW()-ROW($A$6) | G99: =AVERAGE($E$6:$E$98) | H99: =STDEV($E$6:$E$98) | I99: =MIN(MAX((E99-G99)/IF(H99>1e-12,H99,NA()),-8.0),8.0) | J99: =IF(NOT(ISNA(I99)),IF(ABS(I99)>=0.5,"TRIGGER",""),"") | K99: =IF(J99="TRIGGER",IF(I99>0,"LONG","SHORT"),"")
A100: 44958 | B100: Medium | C100: 178 | D100: 106 | E100: =D100-C100 | F100: =ROW()-ROW($A$6) | G100: =AVERAGE($E$6:$E$99) | H100: =STDEV($E$6:$E$99) | I100: =MIN(MAX((E100-G100)/IF(H100>1e-12,H100,NA()),-8.0),8.0) | J100: =IF(NOT(ISNA(I100)),IF(ABS(I100)>=0.5,"TRIGGER",""),"") | K100: =IF(J100="TRIGGER",IF(I100>0,"LONG","SHORT"),"")
A101: 44993 | B101: Medium | C101: 200 | D101: 242 | E101: =D101-C101 | F101: =ROW()-ROW($A$6) | G101: =AVERAGE($E$6:$E$100) | H101: =STDEV($E$6:$E$100) | I101: =MIN(MAX((E101-G101)/IF(H101>1e-12,H101,NA()),-8.0),8.0) | J101: =IF(NOT(ISNA(I101)),IF(ABS(I101)>=0.5,"TRIGGER",""),"") | K101: =IF(J101="TRIGGER",IF(I101>0,"LONG","SHORT"),"")
A102: 45021 | B102: Medium | C102: 200 | D102: 145 | E102: =D102-C102 | F102: =ROW()-ROW($A$6) | G102: =AVERAGE($E$6:$E$101) | H102: =STDEV($E$6:$E$101) | I102: =MIN(MAX((E102-G102)/IF(H102>1e-12,H102,NA()),-8.0),8.0) | J102: =IF(NOT(ISNA(I102)),IF(ABS(I102)>=0.5,"TRIGGER",""),"") | K102: =IF(J102="TRIGGER",IF(I102>0,"LONG","SHORT"),"")
A103: 45049 | B103: Medium | C103: 148 | D103: 296 | E103: =D103-C103 | F103: =ROW()-ROW($A$6) | G103: =AVERAGE($E$6:$E$102) | H103: =STDEV($E$6:$E$102) | I103: =MIN(MAX((E103-G103)/IF(H103>1e-12,H103,NA()),-8.0),8.0) | J103: =IF(NOT(ISNA(I103)),IF(ABS(I103)>=0.5,"TRIGGER",""),"") | K103: =IF(J103="TRIGGER",IF(I103>0,"LONG","SHORT"),"")
A104: 45078 | B104: Medium | C104: 170 | D104: 278 | E104: =D104-C104 | F104: =ROW()-ROW($A$6) | G104: =AVERAGE($E$6:$E$103) | H104: =STDEV($E$6:$E$103) | I104: =MIN(MAX((E104-G104)/IF(H104>1e-12,H104,NA()),-8.0),8.0) | J104: =IF(NOT(ISNA(I104)),IF(ABS(I104)>=0.5,"TRIGGER",""),"") | K104: =IF(J104="TRIGGER",IF(I104>0,"LONG","SHORT"),"")
A105: 45113 | B105: Medium | C105: 228 | D105: 497 | E105: =D105-C105 | F105: =ROW()-ROW($A$6) | G105: =AVERAGE($E$6:$E$104) | H105: =STDEV($E$6:$E$104) | I105: =MIN(MAX((E105-G105)/IF(H105>1e-12,H105,NA()),-8.0),8.0) | J105: =IF(NOT(ISNA(I105)),IF(ABS(I105)>=0.5,"TRIGGER",""),"") | K105: =IF(J105="TRIGGER",IF(I105>0,"LONG","SHORT"),"")
...

Sheet Trigger Check
A1: Trigger Check — formula-computed trigger (live, from Z-Score Calc) vs the strategy's reported trigger (reproduced from fx_strict_battery.py, verified to its saved stats). Any mismatch between B and C is a bug. | M1: 1-pip RT cost (frac) | N1: 7.9464792e-05
A2: Mismatch means the live spreadsheet no longer reproduces the strategy — check the z params or data. | M2: cost cell ref (K col) | N2: $N$1
A4: ADP Employment Change (137 events)
A5: Date | B5: Formula trigger | C5: Reported trigger | D5: z (reported) | E5: Direction | F5: Period | G5: Event close | H5: Next close | I5: Raw move % (formula) | J5: Net % (reported) | K5: Net % (formula)
A6: 42011 | B6: ='Z-Score Calc'!J6 | F6: IS | I6: =IF(AND(ISNUMBER(G6),ISNUMBER(H6)),H6/G6-1,"") | K6: =IF(ISNA(B6),"",IF(B6="TRIGGER",IF(ISNUMBER(I6),SIGN('Z-Score Calc'!I6)*I6-$N$1,""),""))
A7: 42039 | B7: ='Z-Score Calc'!J7 | F7: IS | I7: =IF(AND(ISNUMBER(G7),ISNUMBER(H7)),H7/G7-1,"") | K7: =IF(ISNA(B7),"",IF(B7="TRIGGER",IF(ISNUMBER(I7),SIGN('Z-Score Calc'!I7)*I7-$N$1,""),""))
A8: 42067 | B8: ='Z-Score Calc'!J8 | F8: IS | I8: =IF(AND(ISNUMBER(G8),ISNUMBER(H8)),H8/G8-1,"") | K8: =IF(ISNA(B8),"",IF(B8="TRIGGER",IF(ISNUMBER(I8),SIGN('Z-Score Calc'!I8)*I8-$N$1,""),""))
A9: 42095 | B9: ='Z-Score Calc'!J9 | F9: IS | I9: =IF(AND(ISNUMBER(G9),ISNUMBER(H9)),H9/G9-1,"") | K9: =IF(ISNA(B9),"",IF(B9="TRIGGER",IF(ISNUMBER(I9),SIGN('Z-Score Calc'!I9)*I9-$N$1,""),""))
A10: 42130 | B10: ='Z-Score Calc'!J10 | F10: IS | I10: =IF(AND(ISNUMBER(G10),ISNUMBER(H10)),H10/G10-1,"") | K10: =IF(ISNA(B10),"",IF(B10="TRIGGER",IF(ISNUMBER(I10),SIGN('Z-Score Calc'!I10)*I10-$N$1,""),""))
A11: 42158 | B11: ='Z-Score Calc'!J11 | F11: IS | I11: =IF(AND(ISNUMBER(G11),ISNUMBER(H11)),H11/G11-1,"") | K11: =IF(ISNA(B11),"",IF(B11="TRIGGER",IF(ISNUMBER(I11),SIGN('Z-Score Calc'!I11)*I11-$N$1,""),""))
A12: 42186 | B12: ='Z-Score Calc'!J12 | F12: IS | I12: =IF(AND(ISNUMBER(G12),ISNUMBER(H12)),H12/G12-1,"") | K12: =IF(ISNA(B12),"",IF(B12="TRIGGER",IF(ISNUMBER(I12),SIGN('Z-Score Calc'!I12)*I12-$N$1,""),""))
A13: 42221 | B13: ='Z-Score Calc'!J13 | F13: IS | I13: =IF(AND(ISNUMBER(G13),ISNUMBER(H13)),H13/G13-1,"") | K13: =IF(ISNA(B13),"",IF(B13="TRIGGER",IF(ISNUMBER(I13),SIGN('Z-Score Calc'!I13)*I13-$N$1,""),""))
A14: 42249 | B14: ='Z-Score Calc'!J14 | F14: IS | I14: =IF(AND(ISNUMBER(G14),ISNUMBER(H14)),H14/G14-1,"") | K14: =IF(ISNA(B14),"",IF(B14="TRIGGER",IF(ISNUMBER(I14),SIGN('Z-Score Calc'!I14)*I14-$N$1,""),""))
A15: 42277 | B15: ='Z-Score Calc'!J15 | F15: IS | I15: =IF(AND(ISNUMBER(G15),ISNUMBER(H15)),H15/G15-1,"") | K15: =IF(ISNA(B15),"",IF(B15="TRIGGER",IF(ISNUMBER(I15),SIGN('Z-Score Calc'!I15)*I15-$N$1,""),""))
A16: 42312 | B16: ='Z-Score Calc'!J16 | F16: IS | I16: =IF(AND(ISNUMBER(G16),ISNUMBER(H16)),H16/G16-1,"") | K16: =IF(ISNA(B16),"",IF(B16="TRIGGER",IF(ISNUMBER(I16),SIGN('Z-Score Calc'!I16)*I16-$N$1,""),""))
A17: 42340 | B17: ='Z-Score Calc'!J17 | F17: IS | I17: =IF(AND(ISNUMBER(G17),ISNUMBER(H17)),H17/G17-1,"") | K17: =IF(ISNA(B17),"",IF(B17="TRIGGER",IF(ISNUMBER(I17),SIGN('Z-Score Calc'!I17)*I17-$N$1,""),""))
... A25: 42585 | B25: ='Z-Score Calc'!J25 | F25: IS | I25: =IF(AND(ISNUMBER(G25),ISNUMBER(H25)),H25/G25-1,"") | K25: =IF(ISNA(B25),"",IF(B25="TRIGGER",IF(ISNUMBER(I25),SIGN('Z-Score Calc'!I25)*I25-$N$1,""),""))
A26: 42613 | B26: ='Z-Score Calc'!J26 | D26: 0.026310297 | F26: IS | G26: 103.302 | H26: 103.258 | I26: =IF(AND(ISNUMBER(G26),ISNUMBER(H26)),H26/G26-1,"") | J26: -0.00050538798 | K26: =IF(ISNA(B26),"",IF(B26="TRIGGER",IF(ISNUMBER(I26),SIGN('Z-Score Calc'!I26)*I26-$N$1,""),""))
A27: 42648 | B27: ='Z-Score Calc'!J27 | C27: TRIGGER | D27: -0.68027139 | E27: SHORT | F27: IS | G27: 103.46 | H27: 103.765 | I27: =IF(AND(ISNUMBER(G27),ISNUMBER(H27)),H27/G27-1,"") | J27: -0.003027467 | K27: =IF(ISNA(B27),"",IF(B27="TRIGGER",IF(ISNUMBER(I27),SIGN('Z-Score Calc'!I27)*I27-$N$1,""),""))
A28: 42676 | B28: ='Z-Score Calc'!J28 | C28: TRIGGER | D28: -0.78443148 | E28: SHORT | F28: IS | G28: 104.092 | H28: 103.378 | I28: =IF(AND(ISNUMBER(G28),ISNUMBER(H28)),H28/G28-1,"") | J28: 0.0067798952 | K28: =IF(ISNA(B28),"",IF(B28="TRIGGER",IF(ISNUMBER(I28),SIGN('Z-Score Calc'!I28)*I28-$N$1,""),""))
A29: 42704 | B29: ='Z-Score Calc'!J29 | C29: TRIGGER | D29: 2.1744117 | E29: LONG | F29: IS | G29: 112.47 | H29: 114.694 | I29: =IF(AND(ISNUMBER(G29),ISNUMBER(H29)),H29/G29-1,"") | J29: 0.019694688 | K29: =IF(ISNA(B29),"",IF(B29="TRIGGER",IF(ISNUMBER(I29),SIGN('Z-Score Calc'!I29)*I29-$N$1,""),""))
A30: 42740 | B30: ='Z-Score Calc'!J30 | C30: TRIGGER | D30: -0.75003217 | E30: SHORT | F30: IS | G30: 117.113 | H30: 115.265 | I30: =IF(AND(ISNUMBER(G30),ISNUMBER(H30)),H30/G30-1,"") | J30: 0.015700163 | K30: =IF(ISNA(B30),"",IF(B30="TRIGGER",IF(ISNUMBER(I30),SIGN('Z-Score Calc'!I30)*I30-$N$1,""),""))
A31: 42767 | B31: ='Z-Score Calc'!J31 | C31: TRIGGER | D31: 3.1877525 | E31: LONG | F31: IS | G31: 112.743 | H31: 113.311 | I31: =IF(AND(ISNUMBER(G31),ISNUMBER(H31)),H31/G31-1,"") | J31: 0.0049585492 | K31: =IF(ISNA(B31),"",IF(B31="TRIGGER",IF(ISNUMBER(I31),SIGN('Z-Score Calc'!I31)*I31-$N$1,""),""))
A32: 42802 | B32: ='Z-Score Calc'!J32 | C32: TRIGGER | D32: 3.5652321 | E32: LONG | F32: IS | G32: 113.926 | H32: 114.411 | I32: =IF(AND(ISNUMBER(G32),ISNUMBER(H32)),H32/G32-1,"") | J32: 0.0041776898 | K32: =IF(ISNA(B32),"",IF(B32="TRIGGER",IF(ISNUMBER(I32),SIGN('Z-Score Calc'!I32)*I32-$N$1,""),""))
A33: 42830 | B33: ='Z-Score Calc'!J33 | C33: TRIGGER | D33: 1.9496656 | E33: LONG | F33: IS | G33: 110.381 | H33: 110.897 | I33: =IF(AND(ISNUMBER(G33),ISNUMBER(H33)),H33/G33-1,"") | J33: 0.0045953115 | K33: =IF(ISNA(B33),"",IF(B33="TRIGGER",IF(ISNUMBER(I33),SIGN('Z-Score Calc'!I33)*I33-$N$1,""),""))
A34: 42858 | B34: ='Z-Score Calc'!J34 | D34: -0.23386099 | F34: IS | G34: 112.783 | H34: 112.537 | I34: =IF(AND(ISNUMBER(G34),ISNUMBER(H34)),H34/G34-1,"") | J34: 0.0021016669 | K34: =IF(ISNA(B34),"",IF(B34="TRIGGER",IF(ISNUMBER(I34),SIGN('Z-Score Calc'!I34)*I34-$N$1,""),""))
A35: 42887 | B35: ='Z-Score Calc'!J35 | C35: TRIGGER | D35: 1.6099322 | E35: LONG | F35: IS | G35: 111.437 | H35: 110.463 | I35: =IF(AND(ISNUMBER(G35),ISNUMBER(H35)),H35/G35-1,"") | J35: -0.0088198208 | K35: =IF(ISNA(B35),"",IF(B35="TRIGGER",IF(ISNUMBER(I35),SIGN('Z-Score Calc'!I35)*I35-$N$1,""),""))
A36: 42922 | B36: ='Z-Score Calc'!J36 | C36: TRIGGER | D36: -1.0644308 | E36: SHORT | F36: IS | G36: 113.149 | H36: 113.985 | I36: =IF(AND(ISNUMBER(G36),ISNUMBER(H36)),H36/G36-1,"") | J36: -0.0074679395 | K36: =IF(ISNA(B36),"",IF(B36="TRIGGER",IF(ISNUMBER(I36),SIGN('Z-Score Calc'!I36)*I36-$N$1,""),""))
A37: 42949 | B37: ='Z-Score Calc'!J37 | D37: -0.4857748 | F37: IS | G37: 110.757 | H37: 109.9 | I37: =IF(AND(ISNUMBER(G37),ISNUMBER(H37)),H37/G37-1,"") | J37: 0.0076582153 | K37: =IF(ISNA(B37),"",IF(B37="TRIGGER",IF(ISNUMBER(I37),SIGN('Z-Score Calc'!I37)*I37-$N$1,""),""))
A38: 42977 | B38: ='Z-Score Calc'!J38 | C38: TRIGGER | D38: 1.1995599 | E38: LONG | F38: IS | G38: 110.46 | H38: 110.129 | I38: =IF(AND(ISNUMBER(G38),ISNUMBER(H38)),H38/G38-1,"") | J38: -0.0030760363 | K38: =IF(ISNA(B38),"",IF(B38="TRIGGER",IF(ISNUMBER(I38),SIGN('Z-Score Calc'!I38)*I38-$N$1,""),""))
A39: 43012 | B39: ='Z-Score Calc'!J39 | D39: -0.045515359 | F39: IS | G39: 112.823 | H39: 112.774 | I39: =IF(AND(ISNUMBER(G39),ISNUMBER(H39)),H39/G39-1,"") | J39: 0.00035480812 | K39: =IF(ISNA(B39),"",IF(B39="TRIGGER",IF(ISNUMBER(I39),SIGN('Z-Score Calc'!I39)*I39-$N$1,""),""))
A40: 43040 | B40: ='Z-Score Calc'!J40 | C40: TRIGGER | D40: 0.648434 | E40: LONG | F40: IS | G40: 113.65 | H40: 114.152 | I40: =IF(AND(ISNUMBER(G40),ISNUMBER(H40)),H40/G40-1,"") | J40: 0.0043375954 | K40: =IF(ISNA(B40),"",IF(B40="TRIGGER",IF(ISNUMBER(I40),SIGN('Z-Score Calc'!I40)*I40-$N$1,""),""))
A41: 43075 | B41: ='Z-Score Calc'!J41 | D41: -0.20382665 | F41: IS | G41: 112.464 | H41: 112.291 | I41: =IF(AND(ISNUMBER(G41),ISNUMBER(H41)),H41/G41-1,"") | J41: 0.0014587743 | K41: =IF(ISNA(B41),"",IF(B41="TRIGGER",IF(ISNUMBER(I41),SIGN('Z-Score Calc'!I41)*I41-$N$1,""),""))
A42: 43104 | B42: ='Z-Score Calc'!J42 | C42: TRIGGER | D42: 1.3592902 | E42: LONG | F42: IS | G42: 112.607 | H42: 112.783 | I42: =IF(AND(ISNUMBER(G42),ISNUMBER(H42)),H42/G42-1,"") | J42: 0.0014834475 | K42: =IF(ISNA(B42),"",IF(B42="TRIGGER",IF(ISNUMBER(I42),SIGN('Z-Score Calc'!I42)*I42-$N$1,""),""))
A43: 43131 | B43: ='Z-Score Calc'!J43 | C43: TRIGGER | D43: 0.97143492 | E43: LONG | F43: IS | G43: 108.732 | H43: 109.201 | I43: =IF(AND(ISNUMBER(G43),ISNUMBER(H43)),H43/G43-1,"") | J43: 0.0042338388 | K43: =IF(ISNA(B43),"",IF(B43="TRIGGER",IF(ISNUMBER(I43),SIGN('Z-Score Calc'!I43)*I43-$N$1,""),""))
A44: 43166 | B44: ='Z-Score Calc'!J44 | C44: TRIGGER | D44: 0.72219428 | E44: LONG | F44: IS | G44: 105.537 | H44: 106.186 | I44: =IF(AND(ISNUMBER(G44),ISNUMBER(H44)),H44/G44-1,"") | J44: 0.0060699845 | K44: =IF(ISNA(B44),"",IF(B44="TRIGGER",IF(ISNUMBER(I44),SIGN('Z-Score Calc'!I44)*I44-$N$1,""),""))
A45: 43194 | B45: ='Z-Score Calc'!J45 | C45: TRIGGER | D45: 0.5103638 | E45: LONG | F45: IS | G45: 106.774 | H45: 107.052 | I45: =IF(AND(ISNUMBER(G45),ISNUMBER(H45)),H45/G45-1,"") | J45: 0.0025241641 | K45: =IF(ISNA(B45),"",IF(B45="TRIGGER",IF(ISNUMBER(I45),SIGN('Z-Score Calc'!I45)*I45-$N$1,""),""))
A46: 43222 | B46: ='Z-Score Calc'!J46 | D46: -0.32543988 | F46: IS | G46: 109.827 | H46: 109.096 | I46: =IF(AND(ISNUMBER(G46),ISNUMBER(H46)),H46/G46-1,"") | J46: 0.0065764831 | K46: =IF(ISNA(B46),"",IF(B46="TRIGGER",IF(ISNUMBER(I46),SIGN('Z-Score Calc'!I46)*I46-$N$1,""),""))
A47: 43250 | B47: ='Z-Score Calc'!J47 | C47: TRIGGER | D47: -0.78308695 | E47: SHORT | F47: IS | G47: 108.712 | H47: 108.749 | I47: =IF(AND(ISNUMBER(G47),ISNUMBER(H47)),H47/G47-1,"") | J47: -0.00041983719 | K47: =IF(ISNA(B47),"",IF(B47="TRIGGER",IF(ISNUMBER(I47),SIGN('Z-Score Calc'!I47)*I47-$N$1,""),""))
A48: 43286 | B48: ='Z-Score Calc'!J48 | D48: 0.36338063 | F48: IS | G48: 110.579 | H48: 110.422 | I48: =IF(AND(ISNUMBER(G48),ISNUMBER(H48)),H48/G48-1,"") | J48: -0.0014993122 | K48: =IF(ISNA(B48),"",IF(B48="TRIGGER",IF(ISNUMBER(I48),SIGN('Z-Score Calc'!I48)*I48-$N$1,""),""))
A49: 43313 | B49: ='Z-Score Calc'!J49 | C49: TRIGGER | D49: 0.56391427 | E49: LONG | F49: IS | G49: 111.62 | H49: 111.69 | I49: =IF(AND(ISNUMBER(G49),ISNUMBER(H49)),H49/G49-1,"") | J49: 0.00054766021 | K49: =IF(ISNA(B49),"",IF(B49="TRIGGER",IF(ISNUMBER(I49),SIGN('Z-Score Calc'!I49)*I49-$N$1,""),""))
A50: 43349 | B50: ='Z-Score Calc'!J50 | C50: TRIGGER | D50: -1.2475099 | E50: SHORT | F50: IS | G50: 110.495 | H50: 110.92 | I50: =IF(AND(ISNUMBER(G50),ISNUMBER(H50)),H50/G50-1,"") | J50: -0.0039257512 | K50: =IF(ISNA(B50),"",IF(B50="TRIGGER",IF(ISNUMBER(I50),SIGN('Z-Score Calc'!I50)*I50-$N$1,""),""))
A51: 43376 | B51: ='Z-Score Calc'!J51 | C51: TRIGGER | D51: 0.9030981 | E51: LONG | F51: IS | G51: 114.486 | H51: 113.894 | I51: =IF(AND(ISNUMBER(G51),ISNUMBER(H51)),H51/G51-1,"") | J51: -0.0052504278 | K51: =IF(ISNA(B51),"",IF(B51="TRIGGER",IF(ISNUMBER(I51),SIGN('Z-Score Calc'!I51)*I51-$N$1,""),""))
A52: 43404 | B52: ='Z-Score Calc'!J52 | C52: TRIGGER | D52: 0.67929819 | E52: LONG | F52: IS | G52: 113.052 | H52: 112.851 | I52: =IF(AND(ISNUMBER(G52),ISNUMBER(H52)),H52/G52-1,"") | J52: -0.0018574433 | K52: =IF(ISNA(B52),"",IF(B52="TRIGGER",IF(ISNUMBER(I52),SIGN('Z-Score Calc'!I52)*I52-$N$1,""),""))
A53: 43440 | B53: ='Z-Score Calc'!J53 | C53: TRIGGER | D53: -0.93108587 | E53: SHORT | F53: IS | G53: 113.051 | H53: 112.689 | I53: =IF(AND(ISNUMBER(G53),ISNUMBER(H53)),H53/G53-1,"") | J53: 0.0031226254 | K53: =IF(ISNA(B53),"",IF(B53="TRIGGER",IF(ISNUMBER(I53),SIGN('Z-Score Calc'!I53)*I53-$N$1,""),""))
A54: 43468 | B54: ='Z-Score Calc'!J54 | C54: TRIGGER | D54: 2.3215349 | E54: LONG | F54: IS | G54: 107.441 | H54: 107.808 | I54: =IF(AND(ISNUMBER(G54),ISNUMBER(H54)),H54/G54-1,"") | J54: 0.0033363333 | K54: =IF(ISNA(B54),"",IF(B54="TRIGGER",IF(ISNUMBER(I54),SIGN('Z-Score Calc'!I54)*I54-$N$1,""),""))
A55: 43495 | B55: ='Z-Score Calc'!J55 | C55: TRIGGER | D55: 0.52982931 | E55: LONG | F55: IS | G55: 109.417 | H55: 108.981 | I55: =IF(AND(ISNUMBER(G55),ISNUMBER(H55)),H55/G55-1,"") | J55: -0.004064193 | K55: =IF(ISNA(B55),"",IF(B55="TRIGGER",IF(ISNUMBER(I55),SIGN('Z-Score Calc'!I55)*I55-$N$1,""),""))
A56: 43530 | B56: ='Z-Score Calc'!J56 | C56: TRIGGER | D56: -0.65146062 | E56: SHORT | F56: IS | G56: 111.866 | H56: 111.623 | I56: =IF(AND(ISNUMBER(G56),ISNUMBER(H56)),H56/G56-1,"") | J56: 0.0020927432 | K56: =IF(ISNA(B56),"",IF(B56="TRIGGER",IF(ISNUMBER(I56),SIGN('Z-Score Calc'!I56)*I56-$N$1,""),""))
A57: 43558 | B57: ='Z-Score Calc'!J57 | C57: TRIGGER | D57: -1.6510438 | E57: SHORT | F57: IS | G57: 111.395 | H57: 111.658 | I57: =IF(AND(ISNUMBER(G57),ISNUMBER(H57)),H57/G57-1,"") | J57: -0.002440437 | K57: =IF(ISNA(B57),"",IF(B57="TRIGGER",IF(ISNUMBER(I57),SIGN('Z-Score Calc'!I57)*I57-$N$1,""),""))
A58: 43586 | B58: ='Z-Score Calc'!J58 | C58: TRIGGER | D58: 2.2629878 | E58: LONG | F58: IS | G58: 111.452 | H58: 111.495 | I58: =IF(AND(ISNUMBER(G58),ISNUMBER(H58)),H58/G58-1,"") | J58: 0.00030634494 | K58: =IF(ISNA(B58),"",IF(B58="TRIGGER",IF(ISNUMBER(I58),SIGN('Z-Score Calc'!I58)*I58-$N$1,""),""))
A59: 43621 | B59: ='Z-Score Calc'!J59 | C59: TRIGGER | D59: -4.6358268 | E59: SHORT | F59: IS | G59: 108.328 | H59: 108.454 | I59: =IF(AND(ISNUMBER(G59),ISNUMBER(H59)),H59/G59-1,"") | J59: -0.0012425939 | K59: =IF(ISNA(B59),"",IF(B59="TRIGGER",IF(ISNUMBER(I59),SIGN('Z-Score Calc'!I59)*I59-$N$1,""),""))
A60: 43649 | B60: ='Z-Score Calc'!J60 | C60: TRIGGER | D60: -1.1992948 | E60: SHORT | F60: IS | G60: 107.779 | H60: 107.808 | I60: =IF(AND(ISNUMBER(G60),ISNUMBER(H60)),H60/G60-1,"") | J60: -0.00034852768 | K60: =IF(ISNA(B60),"",IF(B60="TRIGGER",IF(ISNUMBER(I60),SIGN('Z-Score Calc'!I60)*I60-$N$1,""),""))
A61: 43677 | B61: ='Z-Score Calc'!J61 | D61: -0.15336918 | F61: IS | G61: 108.82 | H61: 107.431 | I61: =IF(AND(ISNUMBER(G61),ISNUMBER(H61)),H61/G61-1,"") | J61: 0.012684732 | K61: =IF(ISNA(B61),"",IF(B61="TRIGGER",IF(ISNUMBER(I61),SIGN('Z-Score Calc'!I61)*I61-$N$1,""),""))
A62: 43713 | B62: ='Z-Score Calc'!J62 | C62: TRIGGER | D62: 0.78331383 | E62: LONG | F62: IS | G62: 107.072 | H62: 106.945 | I62: =IF(AND(ISNUMBER(G62),ISNUMBER(H62)),H62/G62-1,"") | J62: -0.0012655723 | K62: =IF(ISNA(B62),"",IF(B62="TRIGGER",IF(ISNUMBER(I62),SIGN('Z-Score Calc'!I62)*I62-$N$1,""),""))
A63: 43740 | B63: ='Z-Score Calc'!J63 | D63: -0.42444402 | F63: IS | G63: 107.163 | H63: 106.826 | I63: =IF(AND(ISNUMBER(G63),ISNUMBER(H63)),H63/G63-1,"") | J63: 0.0030653297 | K63: =IF(ISNA(B63),"",IF(B63="TRIGGER",IF(ISNUMBER(I63),SIGN('Z-Score Calc'!I63)*I63-$N$1,""),""))
A64: 43768 | B64: ='Z-Score Calc'!J64 | D64: -0.183799 | F64: IS | G64: 108.874 | H64: 108.789 | I64: =IF(AND(ISNUMBER(G64),ISNUMBER(H64)),H64/G64-1,"") | J64: 0.00070124579 | K64: =IF(ISNA(B64),"",IF(B64="TRIGGER",IF(ISNUMBER(I64),SIGN('Z-Score Calc'!I64)*I64-$N$1,""),""))
A65: 43803 | B65: ='Z-Score Calc'!J65 | C65: TRIGGER | D65: -2.0414651 | E65: SHORT | F65: IS | G65: 108.653 | H65: 108.832 | I65: =IF(AND(ISNUMBER(G65),ISNUMBER(H65)),H65/G65-1,"") | J65: -0.0017269191 | K65: =IF(ISNA(B65),"",IF(B65="TRIGGER",IF(ISNUMBER(I65),SIGN('Z-Score Calc'!I65)*I65-$N$1,""),""))
A66: 43838 | B66: ='Z-Score Calc'!J66 | C66: TRIGGER | D66: 0.71523227 | E66: LONG | F66: IS | G66: 108.016 | H66: 109.031 | I66: =IF(AND(ISNUMBER(G66),ISNUMBER(H66)),H66/G66-1,"") | J66: 0.0093172857 | K66: =IF(ISNA(B66),"",IF(B66="TRIGGER",IF(ISNUMBER(I66),SIGN('Z-Score Calc'!I66)*I66-$N$1,""),""))
A67: 43866 | B67: ='Z-Score Calc'!J67 | C67: TRIGGER | D67: 2.8762394 | E67: LONG | F67: IS | G67: 109.447 | H67: 109.814 | I67: =IF(AND(ISNUMBER(G67),ISNUMBER(H67)),H67/G67-1,"") | J67: 0.0032737966 | K67: =IF(ISNA(B67),"",IF(B67="TRIGGER",IF(ISNUMBER(I67),SIGN('Z-Score Calc'!I67)*I67-$N$1,""),""))
A68: 43894 | B68: ='Z-Score Calc'!J68 | D68: -0.015666213 | F68: IS | G68: 107.037 | H68: 107.677 | I68: =IF(AND(ISNUMBER(G68),ISNUMBER(H68)),H68/G68-1,"") | J68: -0.0060586998 | K68: =IF(ISNA(B68),"",IF(B68="TRIGGER",IF(ISNUMBER(I68),SIGN('Z-Score Calc'!I68)*I68-$N$1,""),""))
A69: 43922 | B69: ='Z-Score Calc'!J69 | C69: TRIGGER | D69: 2.4325377 | E69: LONG | F69: IS | G69: 107.257 | H69: 108.001 | I69: =IF(AND(ISNUMBER(G69),ISNUMBER(H69)),H69/G69-1,"") | J69: 0.0068571048 | K69: =IF(ISNA(B69),"",IF(B69="TRIGGER",IF(ISNUMBER(I69),SIGN('Z-Score Calc'!I69)*I69-$N$1,""),""))
A70: 43957 | B70: ='Z-Score Calc'!J70 | C70: TRIGGER | D70: -5.3924391 | E70: SHORT | F70: IS | G70: 106.191 | H70: 106.359 | I70: =IF(AND(ISNUMBER(G70),ISNUMBER(H70)),H70/G70-1,"") | J70: -0.0016615128 | K70: =IF(ISNA(B70),"",IF(B70="TRIGGER",IF(ISNUMBER(I70),SIGN('Z-Score Calc'!I70)*I70-$N$1,""),""))
A71: 43985 | B71: ='Z-Score Calc'!J71 | C71: TRIGGER | D71: 8 | E71: LONG | F71: IS | G71: 108.999 | H71: 109.15 | I71: =IF(AND(ISNUMBER(G71),ISNUMBER(H71)),H71/G71-1,"") | J71: 0.001305878 | K71: =IF(ISNA(B71),"",IF(B71="TRIGGER",IF(ISNUMBER(I71),SIGN('Z-Score Calc'!I71)*I71-$N$1,""),""))
A72: 44013 | B72: ='Z-Score Calc'!J72 | C72: TRIGGER | D72: -0.95868522 | E72: SHORT | F72: IS | G72: 107.366 | H72: 107.497 | I72: =IF(AND(ISNUMBER(G72),ISNUMBER(H72)),H72/G72-1,"") | J72: -0.0012996307 | K72: =IF(ISNA(B72),"",IF(B72="TRIGGER",IF(ISNUMBER(I72),SIGN('Z-Score Calc'!I72)*I72-$N$1,""),""))
A73: 44048 | B73: ='Z-Score Calc'!J73 | C73: TRIGGER | D73: -1.8589799 | E73: SHORT | F73: IS | G73: 105.553 | H73: 105.581 | I73: =IF(AND(ISNUMBER(G73),ISNUMBER(H73)),H73/G73-1,"") | J73: -0.00034473321 | K73: =IF(ISNA(B73),"",IF(B73="TRIGGER",IF(ISNUMBER(I73),SIGN('Z-Score Calc'!I73)*I73-$N$1,""),""))
A74: 44076 | B74: ='Z-Score Calc'!J74 | C74: TRIGGER | D74: -0.76225055 | E74: SHORT | F74: IS | G74: 106.208 | H74: 106.086 | I74: =IF(AND(ISNUMBER(G74),ISNUMBER(H74)),H74/G74-1,"") | J74: 0.0010692401 | K74: =IF(ISNA(B74),"",IF(B74="TRIGGER",IF(ISNUMBER(I74),SIGN('Z-Score Calc'!I74)*I74-$N$1,""),""))
A75: 44104 | B75: ='Z-Score Calc'!J75 | D75: 0.043274514 | F75: IS | G75: 105.451 | H75: 105.543 | I75: =IF(AND(ISNUMBER(G75),ISNUMBER(H75)),H75/G75-1,"") | J75: 0.00079300557 | K75: =IF(ISNA(B75),"",IF(B75="TRIGGER",IF(ISNUMBER(I75),SIGN('Z-Score Calc'!I75)*I75-$N$1,""),""))
A76: 44139 | B76: ='Z-Score Calc'!J76 | D76: -0.45337297 | F76: IS | G76: 104.546 | H76: 104.438 | I76: =IF(AND(ISNUMBER(G76),ISNUMBER(H76)),H76/G76-1,"") | J76: 0.00095351669 | K76: =IF(ISNA(B76),"",IF(B76="TRIGGER",IF(ISNUMBER(I76),SIGN('Z-Score Calc'!I76)*I76-$N$1,""),""))
A77: 44167 | B77: ='Z-Score Calc'!J77 | D77: -0.21295874 | F77: IS | G77: 104.309 | H77: 104.458 | I77: =IF(AND(ISNUMBER(G77),ISNUMBER(H77)),H77/G77-1,"") | J77: -0.0015079329 | K77: =IF(ISNA(B77),"",IF(B77="TRIGGER",IF(ISNUMBER(I77),SIGN('Z-Score Calc'!I77)*I77-$N$1,""),""))
A78: 44202 | B78: ='Z-Score Calc'!J78 | D78: -0.35278014 | F78: IS | G78: 102.678 | H78: 103.024 | I78: =IF(AND(ISNUMBER(G78),ISNUMBER(H78)),H78/G78-1,"") | J78: -0.0034492292 | K78: =IF(ISNA(B78),"",IF(B78="TRIGGER",IF(ISNUMBER(I78),SIGN('Z-Score Calc'!I78)*I78-$N$1,""),""))
A79: 44230 | B79: ='Z-Score Calc'!J79 | D79: 0.092378758 | F79: IS | G79: 105.028 | H79: 104.995 | I79: =IF(AND(ISNUMBER(G79),ISNUMBER(H79)),H79/G79-1,"") | J79: -0.00039363941 | K79: =IF(ISNA(B79),"",IF(B79="TRIGGER",IF(ISNUMBER(I79),SIGN('Z-Score Calc'!I79)*I79-$N$1,""),""))
A80: 44258 | B80: ='Z-Score Calc'!J80 | D80: -0.15353536 | F80: IS | G80: 106.758 | H80: 107.058 | I80: =IF(AND(ISNUMBER(G80),ISNUMBER(H80)),H80/G80-1,"") | J80: -0.0028895157 | K80: =IF(ISNA(B80),"",IF(B80="TRIGGER",IF(ISNUMBER(I80),SIGN('Z-Score Calc'!I80)*I80-$N$1,""),""))
A81: 44286 | B81: ='Z-Score Calc'!J81 | D81: -0.11646013 | F81: IS | G81: 110.75 | H81: 110.613 | I81: =IF(AND(ISNUMBER(G81),ISNUMBER(H81)),H81/G81-1,"") | J81: 0.0011575649 | K81: =IF(ISNA(B81),"",IF(B81="TRIGGER",IF(ISNUMBER(I81),SIGN('Z-Score Calc'!I81)*I81-$N$1,""),""))
A82: 44321 | B82: ='Z-Score Calc'!J82 | D82: -0.14928129 | F82: IS | G82: 109.219 | H82: 109.05 | I82: =IF(AND(ISNUMBER(G82),ISNUMBER(H82)),H82/G82-1,"") | J82: 0.0014678733 | K82: =IF(ISNA(B82),"",IF(B82="TRIGGER",IF(ISNUMBER(I82),SIGN('Z-Score Calc'!I82)*I82-$N$1,""),""))
A83: 44350 | B83: ='Z-Score Calc'!J83 | D83: 0.37370019 | F83: IS | G83: 110.266 | H83: 109.617 | I83: =IF(AND(ISNUMBER(G83),ISNUMBER(H83)),H83/G83-1,"") | J83: -0.0059652508 | K83: =IF(ISNA(B83),"",IF(B83="TRIGGER",IF(ISNUMBER(I83),SIGN('Z-Score Calc'!I83)*I83-$N$1,""),""))
A84: 44377 | B84: ='Z-Score Calc'!J84 | D84: 0.0500398 | F84: IS | G84: 111.124 | H84: 111.572 | I84: =IF(AND(ISNUMBER(G84),ISNUMBER(H84)),H84/G84-1,"") | J84: 0.00395205 | K84: =IF(ISNA(B84),"",IF(B84="TRIGGER",IF(ISNUMBER(I84),SIGN('Z-Score Calc'!I84)*I84-$N$1,""),""))
A85: 44412 | B85: ='Z-Score Calc'!J85 | C85: TRIGGER | D85: -0.57579209 | E85: SHORT | F85: IS | G85: 109.529 | H85: 109.752 | I85: =IF(AND(ISNUMBER(G85),ISNUMBER(H85)),H85/G85-1,"") | J85: -0.0021154514 | K85: =IF(ISNA(B85),"",IF(B85="TRIGGER",IF(ISNUMBER(I85),SIGN('Z-Score Calc'!I85)*I85-$N$1,""),""))
A86: 44440 | B86: ='Z-Score Calc'!J86 | D86: -0.39782973 | F86: IS | G86: 110.096 | H86: 109.945 | I86: =IF(AND(ISNUMBER(G86),ISNUMBER(H86)),H86/G86-1,"") | J86: 0.0012920744 | K86: =IF(ISNA(B86),"",IF(B86="TRIGGER",IF(ISNUMBER(I86),SIGN('Z-Score Calc'!I86)*I86-$N$1,""),""))
A87: 44475 | B87: ='Z-Score Calc'!J87 | D87: 0.12874013 | F87: IS | G87: 111.413 | H87: 111.662 | I87: =IF(AND(ISNUMBER(G87),ISNUMBER(H87)),H87/G87-1,"") | J87: 0.0021554678 | K87: =IF(ISNA(B87),"",IF(B87="TRIGGER",IF(ISNUMBER(I87),SIGN('Z-Score Calc'!I87)*I87-$N$1,""),""))
A88: 44503 | B88: ='Z-Score Calc'!J88 | D88: 0.17105133 | F88: IS | G88: 113.962 | H88: 114.07 | I88: =IF(AND(ISNUMBER(G88),ISNUMBER(H88)),H88/G88-1,"") | J88: 0.00086823454 | K88: =IF(ISNA(B88),"",IF(B88="TRIGGER",IF(ISNUMBER(I88),SIGN('Z-Score Calc'!I88)*I88-$N$1,""),""))
A89: 44531 | B89: ='Z-Score Calc'!J89 | D89: -0.056588056 | F89: IS | G89: 113.299 | H89: 112.882 | I89: =IF(AND(ISNUMBER(G89),ISNUMBER(H89)),H89/G89-1,"") | J89: 0.0036010602 | K89: =IF(ISNA(B89),"",IF(B89="TRIGGER",IF(ISNUMBER(I89),SIGN('Z-Score Calc'!I89)*I89-$N$1,""),""))
A90: 44566 | B90: ='Z-Score Calc'!J90 | C90: TRIGGER | D90: 0.50379961 | E90: LONG | F90: OOS | G90: 116.174 | H90: 116.128 | I90: =IF(AND(ISNUMBER(G90),ISNUMBER(H90)),H90/G90-1,"") | J90: -0.00047546775 | K90: =IF(ISNA(B90),"",IF(B90="TRIGGER",IF(ISNUMBER(I90),SIGN('Z-Score Calc'!I90)*I90-$N$1,""),""))
A91: 44594 | B91: ='Z-Score Calc'!J91 | C91: TRIGGER | D91: -0.79323129 | E91: SHORT | F91: OOS | G91: 114.736 | H91: 114.382 | I91: =IF(AND(ISNUMBER(G91),ISNUMBER(H91)),H91/G91-1,"") | J91: 0.0030058465 | K91: =IF(ISNA(B91),"",IF(B91="TRIGGER",IF(ISNUMBER(I91),SIGN('Z-Score Calc'!I91)*I91-$N$1,""),""))
A92: 44622 | B92: ='Z-Score Calc'!J92 | D92: 0.057143286 | F92: OOS | G92: 114.833 | H92: 115.519 | I92: =IF(AND(ISNUMBER(G92),ISNUMBER(H92)),H92/G92-1,"") | J92: 0.0058944017 | K92: =IF(ISNA(B92),"",IF(B92="TRIGGER",IF(ISNUMBER(I92),SIGN('Z-Score Calc'!I92)*I92-$N$1,""),""))
A93: 44650 | B93: ='Z-Score Calc'!J93 | D93: -0.060026857 | F93: OOS | G93: 122.021 | H93: 121.756 | I93: =IF(AND(ISNUMBER(G93),ISNUMBER(H93)),H93/G93-1,"") | J93: 0.00209235 | K93: =IF(ISNA(B93),"",IF(B93="TRIGGER",IF(ISNUMBER(I93),SIGN('Z-Score Calc'!I93)*I93-$N$1,""),""))
A94: 44685 | B94: ='Z-Score Calc'!J94 | D94: -0.2789598 | F94: OOS | G94: 129.22301 | H94: 130.33 | I94: =IF(AND(ISNUMBER(G94),ISNUMBER(H94)),H94/G94-1,"") | J94: -0.0086460092 | K94: =IF(ISNA(B94),"",IF(B94="TRIGGER",IF(ISNUMBER(I94),SIGN('Z-Score Calc'!I94)*I94-$N$1,""),""))
A95: 44714 | B95: ='Z-Score Calc'!J95 | D95: -0.31186098 | F95: OOS | G95: 129.918 | H95: 130.707 | I95: =IF(AND(ISNUMBER(G95),ISNUMBER(H95)),H95/G95-1,"") | J95: -0.0061525376 | K95: =IF(ISNA(B95),"",IF(B95="TRIGGER",IF(ISNUMBER(I95),SIGN('Z-Score Calc'!I95)*I95-$N$1,""),""))
A96: 44839 | B96: ='Z-Score Calc'!J96 | D96: -0.049315844 | F96: OOS | G96: 144.44901 | H96: 145.039 | I96: =IF(AND(ISNUMBER(G96),ISNUMBER(H96)),H96/G96-1,"") | J96: -0.0041639259 | K96: =IF(ISNA(B96),"",IF(B96="TRIGGER",IF(ISNUMBER(I96),SIGN('Z-Score Calc'!I96)*I96-$N$1,""),""))
A97: 44867 | B97: ='Z-Score Calc'!J97 | D97: 0.0033764471 | F97: OOS | G97: 147.91499 | H97: 147.892 | I97: =IF(AND(ISNUMBER(G97),ISNUMBER(H97)),H97/G97-1,"") | J97: -0.00023492567 | K97: =IF(ISNA(B97),"",IF(B97="TRIGGER",IF(ISNUMBER(I97),SIGN('Z-Score Calc'!I97)*I97-$N$1,""),""))
A98: 44895 | B98: ='Z-Score Calc'!J98 | D98: -0.16796021 | F98: OOS | G98: 138.745 | H98: 137.35899 | I98: =IF(AND(ISNUMBER(G98),ISNUMBER(H98)),H98/G98-1,"") | J98: 0.0099100962 | K98: =IF(ISNA(B98),"",IF(B98="TRIGGER",IF(ISNUMBER(I98),SIGN('Z-Score Calc'!I98)*I98-$N$1,""),""))
A99: 44931 | B99: ='Z-Score Calc'!J99 | D99: 0.065546154 | F99: OOS | G99: 132.246 | H99: 133.30701 | I99: =IF(AND(ISNUMBER(G99),ISNUMBER(H99)),H99/G99-1,"") | J99: 0.0079434971 | K99: =IF(ISNA(B99),"",IF(B99="TRIGGER",IF(ISNUMBER(I99),SIGN('Z-Score Calc'!I99)*I99-$N$1,""),""))
A100: 44958 | B100: ='Z-Score Calc'!J100 | D100: -0.16716156 | F100: OOS | G100: 130.11 | H100: 128.62199 | I100: =IF(AND(ISNUMBER(G100),ISNUMBER(H100)),H100/G100-1,"") | J100: 0.011357063 | K100: =IF(ISNA(B100),"",IF(B100="TRIGGER",IF(ISNUMBER(I100),SIGN('Z-Score Calc'!I100)*I100-$N$1,""),""))
A101: 44993 | B101: ='Z-Score Calc'!J101 | D101: 0.0033356184 | F101: OOS | G101: 137.39101 | H101: 137.226 | I101: =IF(AND(ISNUMBER(G101),ISNUMBER(H101)),H101/G101-1,"") | J101: -0.001280479 | K101: =IF(ISNA(B101),"",IF(B101="TRIGGER",IF(ISNUMBER(I101),SIGN('Z-Score Calc'!I101)*I101-$N$1,""),""))
A102: 45021 | B102: ='Z-Score Calc'!J102 | D102: -0.14175574 | F102: OOS | G102: 130.93401 | H102: 131.66901 | I102: =IF(AND(ISNUMBER(G102),ISNUMBER(H102)),H102/G102-1,"") | J102: -0.0056929844 | K102: =IF(ISNA(B102),"",IF(B102="TRIGGER",IF(ISNUMBER(I102),SIGN('Z-Score Calc'!I102)*I102-$N$1,""),""))
A103: 45049 | B103: ='Z-Score Calc'!J103 | D103: 0.16415451 | F103: OOS | G103: 134.54401 | H103: 134.179 | I103: =IF(AND(ISNUMBER(G103),ISNUMBER(H103)),H103/G103-1,"") | J103: -0.0027923727 | K103: =IF(ISNA(B103),"",IF(B103="TRIGGER",IF(ISNUMBER(I103),SIGN('Z-Score Calc'!I103)*I103-$N$1,""),""))
... A141: 46204 | B141: ='Z-Score Calc'!J141 | D141: -0.079503815 | F141: OOS | G141: 162.539 | H141: 161.44901 | I141: =IF(AND(ISNUMBER(G141),ISNUMBER(H141)),H141/G141-1,"") | J141: 0.0066265955 | K141: =IF(ISNA(B141),"",IF(B141="TRIGGER",IF(ISNUMBER(I141),SIGN('Z-Score Calc'!I141)*I141-$N$1,""),""))
A142: 46239 | B142: ='Z-Score Calc'!J142 | D142: -0.098769001 | F142: OOS | G142: 157.76401 | I142: =IF(AND(ISNUMBER(G142),ISNUMBER(H142)),H142/G142-1,"") | K142: =IF(ISNA(B142),"",IF(B142="TRIGGER",IF(ISNUMBER(I142),SIGN('Z-Score Calc'!I142)*I142-$N$1,""),""))
A143: API Crude Oil Stock Change (288 events)
A144: Date | B144: Formula trigger | C144: Reported trigger | D144: z (reported) | E144: Direction | F144: Period | G144: Event close | H144: Next close | I144: Raw move % (formula) | J144: Net % (reported) | K144: Net % (formula)
A145: 43096 | B145: ='Z-Score Calc'!J145 | F145: IS | G145: 113.203 | H145: 113.217 | I145: =IF(AND(ISNUMBER(G145),ISNUMBER(H145)),H145/G145-1,"") | K145: =IF(ISNA(B145),"",IF(B145="TRIGGER",IF(ISNUMBER(I145),SIGN('Z-Score Calc'!I145)*I145-$N$1,""),""))
...

Sheet Instructions
A1: USDJPY NEWS UNDER-REACTION DRIFT — the rule, from code (ground truth: E:/forex-data/scripts/fx_strict_battery.py)
A3: 1. THE RULE (plain English)
A4: - Universe: every US (currency=USD) economic release tagged High or Medium impact that has a
A5: numeric forecast AND numeric actual in the Forex Factory archive.
A6: - Surprise = actual - forecast (as printed, numeric only).
A7: - For each release title (e.g. Non Farm Payrolls) separately, compute a trailing z-score using ONLY
A8: that title's own earlier surprises: z = (surprise - mean of prior surprises) / std of prior surprises.
A9: - Needs at least 20 prior surprises of the same title (otherwise no z = no trade).
A10: - Standard deviation floored at 1e-12 (a constant-surprise title never trades).
A11: - z clipped to +/-8.
A12: - TRIGGER: |z| >= 0.5. Direction: LONG USDJPY if z > 0, SHORT USDJPY if z < 0.
A14: 2. ENTRY / EXIT — exact timing (this is where the README label is imprecise)
... A60: - Headline stats reproduce the battery's saved numbers exactly.
